_quicktex.cpython-312-darwin.so
quicktex/image_utils.py
quicktex/__init__.py
quicktex/py.typed
quicktex/dds.py
quicktex/__main__.py
quicktex/cli/encode.py
quicktex/cli/__init__.py
quicktex/cli/common.py
quicktex/cli/decode.py
quicktex/.dylibs/libomp.dylib
quicktex/s3tc/__init__.py
quicktex/s3tc/bc1/__init__.py
quicktex/s3tc/interpolator/__init__.py
quicktex/s3tc/bc5/__init__.py
quicktex/s3tc/bc3/__init__.py
quicktex/s3tc/bc4/__init__.py
quicktex-0.3.1.dist-info/LICENSE.md
quicktex-0.3.1.dist-info/RECORD
quicktex-0.3.1.dist-info/WHEEL
quicktex-0.3.1.dist-info/entry_points.txt
quicktex-0.3.1.dist-info/top_level.txt
quicktex-0.3.1.dist-info/METADATA
