Metadata-Version: 2.1
Name: quicktex
Version: 0.3.1
Summary: A fast block compression library for python
Author-email: Andrew Cassidy <drewcassidy@me.com>
Project-URL: Docs, https://quicktex.readthedocs.io/en/latest/
Project-URL: Source, https://github.com/drewcassidy/quicktex
Project-URL: Changelog, https://github.com/drewcassidy/quicktex/blob/main/CHANGELOG.md
Classifier: Development Status :: 3 - Alpha
Classifier: Intended Audience :: Developers
Classifier: License :: OSI Approved :: Apache Software License
Classifier: Operating System :: OS Independent
Classifier: Programming Language :: Python :: 3 :: Only
Classifier: Programming Language :: Python :: 3
Classifier: Topic :: Multimedia :: Graphics :: Graphics Conversion
Classifier: Programming Language :: Python :: Implementation :: CPython
Classifier: Programming Language :: C++
Requires-Python: >=3.9
License-File: LICENSE.md
Requires-Dist: Pillow
Requires-Dist: click
Provides-Extra: docs
Requires-Dist: Sphinx>=3.5; extra == "docs"
Requires-Dist: sphinx-click>=2.7; extra == "docs"
Requires-Dist: sphinx-rtd-theme; extra == "docs"
Requires-Dist: myst-parser>=0.14; extra == "docs"
Provides-Extra: stubs
Requires-Dist: pybind11-stubgen; extra == "stubs"
Provides-Extra: tests
Requires-Dist: parameterized; extra == "tests"
Requires-Dist: pytest; extra == "tests"
